LICENSE
README.md
kimola/__init__.py
kimola/client.py
kimola/config.py
kimola/transport.py
kimola/models/__init__.py
kimola/resources/presets.py
kimola/resources/queries.py
kimola/resources/subscription.py
kimola-0.1.1.dist-info/METADATA
kimola-0.1.1.dist-info/WHEEL
kimola-0.1.1.dist-info/licenses/LICENSE
kimola-0.1.1.dist-info/RECORD
