Metadata-Version: 2.4
Name: kimola
Version: 0.1.1
Summary: Kimola API SDK for Python
Project-URL: Homepage, https://github.com/Kimola/api
Project-URL: Issues, https://github.com/Kimola/api/issues
Author-email: Kimola <developer@kimola.com>
License: MIT License
License-File: LICENSE
Keywords: api,classification,kimola,nlp,sdk,sentiment
Classifier: License :: OSI Approved :: MIT License
Classifier: Operating System :: OS Independent
Classifier: Programming Language :: Python :: 3
Classifier: Typing :: Typed
Requires-Python: >=3.8
Requires-Dist: httpx<1.0,>=0.27
Requires-Dist: pydantic<3.0,>=2.5
